dynasaur/__init__.py
dynasaur/calc/__init__.py
dynasaur/calc/cfc.py
dynasaur/calc/object_calculation_util.py
dynasaur/calc/risk_function_util.py
dynasaur/calc/standard_functions.py
dynasaur/data/__init__.py
dynasaur/data/data_container.py
dynasaur/data/data_interface.py
dynasaur/data/dynasaur_definitions.py
dynasaur/data/ls_dyna.py
dynasaur/data/madymo.py
dynasaur/data/vps.py
dynasaur/io/ISO_MME_Converter.py
dynasaur/io/__init__.py
dynasaur/plugins/__init__.py
dynasaur/plugins/criteria_controller.py
dynasaur/plugins/data_visualization_controller.py
dynasaur/plugins/plugin.py
dynasaur/utils/__init__.py
dynasaur/utils/constants.py
dynasaur/utils/logger.py
dynasaur/utils/units.py
dynasaur-1.4.0.dist-info/LICENSE
dynasaur-1.4.0.dist-info/METADATA
dynasaur-1.4.0.dist-info/WHEEL
dynasaur-1.4.0.dist-info/top_level.txt
dynasaur-1.4.0.dist-info/RECORD
