Metadata-Version: 2.1
Name: dynasaur
Version: 1.4.0
Summary: Postprocessing assessment tool
Home-page: https://gitlab.com/VSI-TUGraz/Dynasaur
Author: VSI, TU GRAZ
Author-email: vsi.office@tugraz.at
License: GPL-v3
Classifier: Topic :: Scientific/Engineering
Classifier: Intended Audience :: Science/Research
Classifier: Programming Language :: Python :: 3
Classifier: Programming Language :: Python :: 3.5
Classifier: Programming Language :: Python :: 3.6
Classifier: Programming Language :: Python :: 3.7
Classifier: Programming Language :: Python :: 3.8
Classifier: License :: OSI Approved :: GNU General Public License v3 (GPLv3)
Classifier: Operating System :: Microsoft :: Windows
Classifier: Operating System :: POSIX :: Linux
Requires-Python: >=3.5
License-File: LICENSE
Requires-Dist: sklearn ==0.0
Requires-Dist: numpy <2.0
Requires-Dist: scipy ==1.13
Requires-Dist: colorama
Requires-Dist: termcolor
Requires-Dist: lasso-python ==1.5.0
Requires-Dist: pint
